TakeSpellChecker/__init__.py
TakeSpellChecker/spellcheck.py
TakeSpellChecker-0.0.5.dist-info/LICENSE
TakeSpellChecker-0.0.5.dist-info/METADATA
TakeSpellChecker-0.0.5.dist-info/WHEEL
TakeSpellChecker-0.0.5.dist-info/top_level.txt
TakeSpellChecker-0.0.5.dist-info/RECORD
