Metadata-Version: 2.1
Name: TakeSpellChecker
Version: 0.0.5
Summary: Machine learning spell check package that combines word's context with characters similarity.
Home-page: https://github.com/karinatk/TakeSpellChecker
Author: Karina Tiemi Kato
Author-email: karinatkato@gmail.com
License: UNKNOWN
Platform: UNKNOWN
Classifier: Programming Language :: Python :: 3
Classifier: License :: OSI Approved :: MIT License
Classifier: Operating System :: OS Independent
Requires-Dist: numpy
Requires-Dist: pandas
Requires-Dist: gensim
Requires-Dist: pyjarowinkler
Requires-Dist: azure-storage-file
Requires-Dist: PyYAML
